{
    "id": "a4008f9b-df0e-4cec-beb9-8ccce83e1ff4",
    "name": [
        {
            "languageCode": "nb",
            "languageText": "oppholdsadresse ajourholdstidspunkt"
        }
    ],
    "description": [
        {
            "languageCode": "nb",
            "languageText": "FregPersondokumentMedHistorikk - oppholdsadresse, ajourholdstidspunkt"
        }
    ],
    "administrativeStatus": "DRAFT",
    "versionValidFrom": "2019-06-07T08:34:00.000Z",
    "validFrom": "2019-06-07T08:34:00.000Z",
    "createdDate": "2019-06-07T08:34:00.000Z",
    "createdBy": "BNJ",
    "representedVariable": "/RepresentedVariable/RepresentertVariable_DUMMY",
    "population": "/Population/2aa9ab12-63ca-4458-aa00-95ea287bf2a5",
    "dataStructureComponentType": "MEASURE",
    "shortName": "OPPHOLDSADRESSE_AJOURHOLDSTIDSPUNKT"
}