{
    "id": "5588a379-9490-4e7e-b630-cd368921cb59",
    "name": [
        {
            "languageCode": "nb",
            "languageText": "oppholdsadresse matrikkeladresse undernummer"
        }
    ],
    "description": [
        {
            "languageCode": "nb",
            "languageText": "FregPersondokumentMedHistorikk - oppholdsadresse, matrikkeladresse undernummer"
        }
    ],
    "administrativeStatus": "DRAFT",
    "versionValidFrom": "2019-06-07T08:34:01.000Z",
    "validFrom": "2019-06-07T08:34:01.000Z",
    "createdDate": "2019-06-07T08:34:01.000Z",
    "createdBy": "BNJ",
    "representedVariable": "/RepresentedVariable/RepresentertVariable_DUMMY",
    "population": "/Population/2aa9ab12-63ca-4458-aa00-95ea287bf2a5",
    "dataStructureComponentType": "MEASURE",
    "shortName": "OPPHOLDSADRESSE_MATRIKKELADRESSE_UNDERNUMMER"
}