{
    "id": "09565432-a618-400d-ac4e-b06dd2323d31",
    "name": [
        {
            "languageCode": "nb",
            "languageText": "bibehold foedselsEllerDNummer"
        }
    ],
    "description": [
        {
            "languageCode": "nb",
            "languageText": "FREG bibehold foedsels eller dnummer"
        }
    ],
    "administrativeStatus": "DRAFT",
    "versionValidFrom": "2019-05-01T15:49:06.000Z",
    "validFrom": "2019-05-01T15:49:06.000Z",
    "createdDate": "2019-05-01T15:49:06.000Z",
    "createdBy": "BNJ",
    "representedVariable": "/RepresentedVariable/DRAFT",
    "population": "/Population/2aa9ab12-63ca-4458-aa00-95ea287bf2a5",
    "dataStructureComponentType": "IDENTIFIER",
    "shortName": "BIBEHOLD_FOEDSELSELLERDNUMMER",
    "dataStructureComponentRole": "ENTITY"
}