{
    "id": "9bf188e2-56dd-4f9b-8581-5f928b507312",
    "name": [
        {
            "languageCode": "nb",
            "languageText": "kontaktinformasjonForDoedsbo organisasjon organisasjonsnavn"
        }
    ],
    "description": [
        {
            "languageCode": "nb",
            "languageText": "FREG kontaktinformasjonForDoedsbo organisasjon organisasjonsnavn"
        }
    ],
    "administrativeStatus": "DRAFT",
    "versionValidFrom": "2019-04-26T13:24:36.000Z",
    "validFrom": "2019-04-26T13:24:36.000Z",
    "createdDate": "2019-04-26T13:24:36.000Z",
    "createdBy": "BNJ",
    "representedVariable": "/RepresentedVariable/DRAFT",
    "population": "/Population/2aa9ab12-63ca-4458-aa00-95ea287bf2a5",
    "dataStructureComponentType": "MEASURE",
    "shortName": "KONTAKTINFORMASJONFORDOEDSBO_ORGANISASJON_ORGANISASJONSNAVN"
}