{
    "id": "89621851-612a-4223-92d7-4324a45c47f7",
    "name": [
        {
            "languageCode": "nb",
            "languageText": "kontaktinformasjonForDoedsbo aarsak"
        }
    ],
    "description": [
        {
            "languageCode": "nb",
            "languageText": "FREG kontaktinformasjonForDoedsbo aarsak"
        }
    ],
    "administrativeStatus": "DRAFT",
    "versionValidFrom": "2019-03-29T15:56:41.000Z",
    "validFrom": "2019-03-29T15:56:41.000Z",
    "createdDate": "2019-03-29T15:56:41.000Z",
    "createdBy": "BNJ",
    "representedVariable": "/RepresentedVariable/DRAFT",
    "shortName": "KONTAKTINFORMASJONFORDOEDSBO_AARSAK"
}