{
    "id": "fd3e1bdd-ce5b-40a2-9d3b-4f30a934fb31",
    "name": [
        {
            "languageCode": "nb",
            "languageText": "konto tilbakefoerteRenter"
        }
    ],
    "description": [
        {
            "languageCode": "nb",
            "languageText": "UttrekkSkattemelding v0_18 - konto, tilbakefoerte renter"
        }
    ],
    "administrativeStatus": "DRAFT",
    "versionValidFrom": "2019-07-01T13:48:44.000Z",
    "validFrom": "2019-07-01T13:48:44.000Z",
    "createdDate": "2019-07-01T13:48:44.000Z",
    "createdBy": "BNJ",
    "representedVariable": "/RepresentedVariable/RepresentertVariable_DUMMY",
    "population": "/Population/Population_DUMMY",
    "dataStructureComponentType": "MEASURE",
    "shortName": "KONTO_TILBAKEFOERTERENTER"
}