{
    "id": "bac985f4-6fbc-41c9-a69b-d449d4dc827d",
    "name": [
        {
            "languageCode": "nb",
            "languageText": "postadresseIUtlandet adressegradering"
        }
    ],
    "description": [
        {
            "languageCode": "nb",
            "languageText": "FREG postadresseIUtlandet adressegradering"
        }
    ],
    "administrativeStatus": "DRAFT",
    "versionValidFrom": "2019-04-26T13:24:41.000Z",
    "validFrom": "2019-04-26T13:24:41.000Z",
    "createdDate": "2019-04-26T13:24:41.000Z",
    "createdBy": "BNJ",
    "representedVariable": "/RepresentedVariable/DRAFT",
    "population": "/Population/2aa9ab12-63ca-4458-aa00-95ea287bf2a5",
    "dataStructureComponentType": "MEASURE",
    "shortName": "POSTADRESSEIUTLANDET_ADRESSEGRADERING"
}