{
    "id": "5e8238d1-5748-4ed9-bd2e-67df0c25c942",
    "name": [
        {
            "languageCode": "nb",
            "languageText": "arbeidsoppholdUtenforHjemmet merkostnadForLosjiVedArbeidsoppholdUtenforHjemmet"
        }
    ],
    "description": [
        {
            "languageCode": "nb",
            "languageText": "Skattemelding - arbeidsopphold utenfor hjemmet, merkostnad for losji ved arbeidsopphold utenfor hjemmet"
        }
    ],
    "administrativeStatus": "DRAFT",
    "versionValidFrom": "2019-05-24T16:03:31.000Z",
    "validFrom": "2019-05-24T16:03:31.000Z",
    "createdDate": "2019-05-24T16:03:31.000Z",
    "createdBy": "BNJ",
    "representedVariable": "/RepresentedVariable/DRAFT",
    "population": "/Population/2aa9ab12-63ca-4458-aa00-95ea287bf2a5",
    "dataStructureComponentType": "MEASURE",
    "shortName": "ARBEIDSOPPHOLDUTENFORHJEMMET_MERKOSTNADFORLOSJIVEDARBEIDSOPPHOLDUTENFORHJEMMET"
}