{
    "id": "1663bd1c-45e9-491a-8af3-1c8b10d3aff7",
    "name": [
        {
            "languageCode": "nb",
            "languageText": "identitetsgrunnlag foedselsEllerDNummer"
        }
    ],
    "description": [
        {
            "languageCode": "nb",
            "languageText": "FREG identitetsgrunnlag foedsels eller dnummer"
        }
    ],
    "administrativeStatus": "DRAFT",
    "versionValidFrom": "2019-04-09T13:00:22.000Z",
    "validFrom": "2019-04-09T13:00:22.000Z",
    "createdDate": "2019-04-09T13:00:22.000Z",
    "createdBy": "BNJ",
    "representedVariable": "/RepresentedVariable/DRAFT",
    "population": "/Population/2aa9ab12-63ca-4458-aa00-95ea287bf2a5",
    "dataStructureComponent": "/IdentifierComponent/0bced9b5-8768-406b-9793-b453a56d2756"
}