{
    "id": "343ece89-1e50-4005-9a48-62346816f1c3",
    "name": [
        {
            "languageCode": "nb",
            "languageText": "falskIdentitet rettIdentitetVedOpplysninger personnavn etternavn"
        }
    ],
    "description": [
        {
            "languageCode": "nb",
            "languageText": "FREG falskIdentitet rettIdentitetVedOpplysninger personnavn etternavn"
        }
    ],
    "administrativeStatus": "DRAFT",
    "versionValidFrom": "2019-03-29T15:56:40.000Z",
    "validFrom": "2019-03-29T15:56:40.000Z",
    "createdDate": "2019-03-29T15:56:40.000Z",
    "createdBy": "BNJ",
    "representedVariable": "/RepresentedVariable/DRAFT",
    "population": "/Population/2aa9ab12-63ca-4458-aa00-95ea287bf2a5",
    "dataStructureComponent": "/MeasureComponent/7277c762-b8e8-402a-9519-24936db36222"
}