{
    "id": "13682c23-2f6b-4e3b-bd44-b600c492f9fb",
    "name": [
        {
            "languageCode": "nb",
            "languageText": "falskIdentitet opphoerstidspunkt"
        }
    ],
    "description": [
        {
            "languageCode": "nb",
            "languageText": "FREG falskIdentitet opphoerstidspunkt"
        }
    ],
    "administrativeStatus": "DRAFT",
    "versionValidFrom": "2019-04-26T13:24:36.000Z",
    "validFrom": "2019-04-26T13:24:36.000Z",
    "createdDate": "2019-04-26T13:24:36.000Z",
    "createdBy": "BNJ",
    "representedVariable": "/RepresentedVariable/DRAFT",
    "population": "/Population/2aa9ab12-63ca-4458-aa00-95ea287bf2a5",
    "dataStructureComponentType": "MEASURE",
    "shortName": "FALSKIDENTITET_OPPHOERSTIDSPUNKT"
}