{
    "id": "f39f29d3-54cb-4ee1-9ed8-108ce16009f0",
    "name": [
        {
            "languageCode": "nb",
            "languageText": "falskIdentitet rettIdentitetVedOpplysninger personnavn fornavn"
        }
    ],
    "description": [
        {
            "languageCode": "nb",
            "languageText": "FREG falskIdentitet rettIdentitetVedOpplysninger personnavn fornavn"
        }
    ],
    "administrativeStatus": "DRAFT",
    "versionValidFrom": "2019-04-09T13:00:21.000Z",
    "validFrom": "2019-04-09T13:00:21.000Z",
    "createdDate": "2019-04-09T13:00:21.000Z",
    "createdBy": "BNJ",
    "representedVariable": "/RepresentedVariable/DRAFT",
    "shortName": "FALSKIDENTITET_RETTIDENTITETVEDOPPLYSNINGER_PERSONNAVN_FORNAVN"
}