{
    "id": "42ab4945-3c49-4f5a-8a4f-5fe1b64a2f13",
    "name": [
        {
            "languageCode": "nb",
            "languageText": "utenlandskPersonidentifikasjon erGjeldende"
        }
    ],
    "description": [
        {
            "languageCode": "nb",
            "languageText": "FREG utenlandskPersonidentifikasjon er gjeldende"
        }
    ],
    "administrativeStatus": "DRAFT",
    "versionValidFrom": "2019-04-26T13:24:37.000Z",
    "validFrom": "2019-04-26T13:24:37.000Z",
    "createdDate": "2019-04-26T13:24:37.000Z",
    "createdBy": "BNJ",
    "representedVariable": "/RepresentedVariable/DRAFT",
    "population": "/Population/2aa9ab12-63ca-4458-aa00-95ea287bf2a5",
    "dataStructureComponentType": "MEASURE",
    "shortName": "UTENLANDSKPERSONIDENTIFIKASJON_ERGJELDENDE"
}