{
    "id": "cb5de2ed-cb99-4bdb-a0d3-c4d5d849b2d4",
    "name": [
        {
            "languageCode": "nb",
            "languageText": "utenlandskPersonidentifikasjon aarsak"
        }
    ],
    "description": [
        {
            "languageCode": "nb",
            "languageText": "FREG utenlandskPersonidentifikasjon aarsak"
        }
    ],
    "administrativeStatus": "DRAFT",
    "versionValidFrom": "2019-03-29T15:56:42.000Z",
    "validFrom": "2019-03-29T15:56:42.000Z",
    "createdDate": "2019-03-29T15:56:42.000Z",
    "createdBy": "BNJ",
    "representedVariable": "/RepresentedVariable/DRAFT",
    "shortName": "UTENLANDSKPERSONIDENTIFIKASJON_AARSAK"
}