{
    "id": "26f48afe-d5d6-4fa3-9bb1-534530a16765",
    "name": [
        {
            "languageCode": "nb",
            "languageText": "bostedsadresse adresseIdentifikatorFraMatrikkelen"
        }
    ],
    "description": [
        {
            "languageCode": "nb",
            "languageText": "FREG bostedsadresse adresse identifikator fra matrikkelen"
        }
    ],
    "administrativeStatus": "DRAFT",
    "versionValidFrom": "2019-03-28T11:05:12.000Z",
    "validFrom": "2019-03-28T11:05:12.000Z",
    "createdDate": "2019-03-28T11:05:12.000Z",
    "createdBy": "BNJ",
    "representedVariable": "/RepresentedVariable/DRAFT",
    "population": "/Population/2aa9ab12-63ca-4458-aa00-95ea287bf2a5",
    "dataStructureComponent": "/MeasureComponent/98dff3ba-ac73-44b1-9a13-60a4ebc88a83"
}