{
    "id": "6f29acc8-6fde-451b-93d5-f0c7acc23ca8",
    "name": [
        {
            "languageCode": "nb",
            "languageText": "bostedsadresse naerAdresseIdentifikatorFraMatrikkelen"
        }
    ],
    "description": [
        {
            "languageCode": "nb",
            "languageText": "FREG bostedsadresse naer adresse identifikator fra matrikkelen"
        }
    ],
    "administrativeStatus": "DRAFT",
    "versionValidFrom": "2019-03-28T11:05:12.000Z",
    "validFrom": "2019-03-28T11:05:12.000Z",
    "createdDate": "2019-03-28T11:05:12.000Z",
    "createdBy": "BNJ",
    "representedVariable": "/RepresentedVariable/DRAFT",
    "population": "/Population/2aa9ab12-63ca-4458-aa00-95ea287bf2a5",
    "dataStructureComponent": "/MeasureComponent/3ffd1adb-c497-4115-8190-53ccfd6bcbdc"
}