{
    "id": "20ff0314-88f2-48dd-9074-f313ee70daeb",
    "name": [
        {
            "languageCode": "nb",
            "languageText": "bostedsadresse foedselsEllerDNummer"
        }
    ],
    "description": [
        {
            "languageCode": "nb",
            "languageText": "FREG bostedsadresse foedsels eller dnummer"
        }
    ],
    "administrativeStatus": "DRAFT",
    "versionValidFrom": "2019-05-01T15:49:01.000Z",
    "validFrom": "2019-05-01T15:49:01.000Z",
    "createdDate": "2019-05-01T15:49:01.000Z",
    "createdBy": "BNJ",
    "representedVariable": "/RepresentedVariable/DRAFT",
    "population": "/Population/2aa9ab12-63ca-4458-aa00-95ea287bf2a5",
    "dataStructureComponentType": "IDENTIFIER",
    "shortName": "BOSTEDSADRESSE_FOEDSELSELLERDNUMMER",
    "dataStructureComponentRole": "ENTITY"
}