{
    "id": "f92c3269-b531-40ba-b506-d3f42b857d32",
    "name": [
        {
            "languageCode": "nb",
            "languageText": "bostedsadresse vegadresse adressenummer husbokstav"
        }
    ],
    "description": [
        {
            "languageCode": "nb",
            "languageText": "FREG bostedsadresse vegadresse adressenummer husbokstav"
        }
    ],
    "administrativeStatus": "DRAFT",
    "versionValidFrom": "2019-03-29T15:56:43.000Z",
    "validFrom": "2019-03-29T15:56:43.000Z",
    "createdDate": "2019-03-29T15:56:43.000Z",
    "createdBy": "BNJ",
    "representedVariable": "/RepresentedVariable/DRAFT",
    "shortName": "BOSTEDSADRESSE_VEGADRESSE_ADRESSENUMMER_HUSBOKSTAV"
}