{
    "id": "e8447dde-6982-47fb-9383-cc4c2c11f677",
    "name": [
        {
            "languageCode": "nb",
            "languageText": "kollektivPensjonsordning pensjonsutbetalersNavn"
        }
    ],
    "description": [
        {
            "languageCode": "nb",
            "languageText": "Skattemelding - kollektiv pensjonsordning, pensjonsutbetalers navn"
        }
    ],
    "administrativeStatus": "DRAFT",
    "versionValidFrom": "2019-05-24T16:03:37.000Z",
    "validFrom": "2019-05-24T16:03:37.000Z",
    "createdDate": "2019-05-24T16:03:37.000Z",
    "createdBy": "BNJ",
    "representedVariable": "/RepresentedVariable/DRAFT",
    "population": "/Population/2aa9ab12-63ca-4458-aa00-95ea287bf2a5",
    "dataStructureComponentType": "MEASURE",
    "shortName": "KOLLEKTIVPENSJONSORDNING_PENSJONSUTBETALERSNAVN"
}