{
    "id": "bbfda88a-9d9e-4502-8a11-3cbc1c569864",
    "name": [
        {
            "languageCode": "nb",
            "languageText": "kjoenn erGjeldende"
        }
    ],
    "description": [
        {
            "languageCode": "nb",
            "languageText": "FREG kjoenn er gjeldende"
        }
    ],
    "administrativeStatus": "DRAFT",
    "versionValidFrom": "2019-04-09T13:00:27.000Z",
    "validFrom": "2019-04-09T13:00:27.000Z",
    "createdDate": "2019-04-09T13:00:27.000Z",
    "createdBy": "BNJ",
    "representedVariable": "/RepresentedVariable/DRAFT",
    "shortName": "KJOENN_ERGJELDENDE"
}