{
    "id": "61d198f1-60d2-4d5c-9d6d-118eee1389c0",
    "name": [
        {
            "languageCode": "nb",
            "languageText": "doedsfall"
        }
    ],
    "description": [
        {
            "languageCode": "nb",
            "languageText": "FREG datastruktur doedsfall"
        }
    ],
    "administrativeStatus": "DRAFT",
    "versionValidFrom": "2019-04-09T13:00:23.000Z",
    "validFrom": "2019-04-09T13:00:23.000Z",
    "createdDate": "2019-04-09T13:00:23.000Z",
    "createdBy": "BNJ",
    "logicalRecords": [
        "/LogicalRecord/a1cb3956-17ee-4608-a83d-12b10ff5b744"
    ]
}