{
    "id": "3bf714c6-d7e3-47ff-b7b3-69f5fa7c9c15",
    "name": [
        {
            "languageCode": "nb",
            "languageText": "legitimasjonsdokument identifikasjonsdokumentnummer"
        }
    ],
    "description": [
        {
            "languageCode": "nb",
            "languageText": "FREG legitimasjonsdokument identifikasjonsdokumentnummer"
        }
    ],
    "administrativeStatus": "DRAFT",
    "versionValidFrom": "2019-03-29T15:56:41.000Z",
    "validFrom": "2019-03-29T15:56:41.000Z",
    "createdDate": "2019-03-29T15:56:41.000Z",
    "createdBy": "BNJ",
    "representedVariable": "/RepresentedVariable/DRAFT",
    "population": "/Population/2aa9ab12-63ca-4458-aa00-95ea287bf2a5",
    "dataStructureComponent": "/MeasureComponent/4729bdad-e9cc-4698-aa02-6201a30a211f"
}