{
    "id": "aa4d3a54-3c42-437b-8def-452a354b924d",
    "name": [
        {
            "languageCode": "nb",
            "languageText": "deltBosted matrikkeladresse poststed poststedsnavn"
        }
    ],
    "description": [
        {
            "languageCode": "nb",
            "languageText": "FREG deltBosted matrikkeladresse poststed poststedsnavn"
        }
    ],
    "administrativeStatus": "DRAFT",
    "versionValidFrom": "2019-04-26T13:24:39.000Z",
    "validFrom": "2019-04-26T13:24:39.000Z",
    "createdDate": "2019-04-26T13:24:39.000Z",
    "createdBy": "BNJ",
    "representedVariable": "/RepresentedVariable/DRAFT",
    "population": "/Population/2aa9ab12-63ca-4458-aa00-95ea287bf2a5",
    "dataStructureComponentType": "MEASURE",
    "shortName": "DELTBOSTED_MATRIKKELADRESSE_POSTSTED_POSTSTEDSNAVN"
}