{
    "id": "67b70f03-e6dd-40cc-8dec-251e7b360582",
    "name": [
        {
            "languageCode": "nb",
            "languageText": "deltBosted matrikkeladresse matrikkelnummer kommunenummer"
        }
    ],
    "description": [
        {
            "languageCode": "nb",
            "languageText": "FREG deltBosted matrikkeladresse matrikkelnummer kommunenummer"
        }
    ],
    "administrativeStatus": "DRAFT",
    "versionValidFrom": "2019-03-29T15:56:43.000Z",
    "validFrom": "2019-03-29T15:56:43.000Z",
    "createdDate": "2019-03-29T15:56:43.000Z",
    "createdBy": "BNJ",
    "representedVariable": "/RepresentedVariable/DRAFT",
    "population": "/Population/2aa9ab12-63ca-4458-aa00-95ea287bf2a5",
    "dataStructureComponent": "/MeasureComponent/e188b14b-e093-4593-8f6d-2174e1eae385"
}