{
    "id": "71e359db-ff38-40fb-9785-32744a973147",
    "name": [
        {
            "languageCode": "nb",
            "languageText": "skattepliktigKundeutbytteUtenforVirksomhetPerUtbetaler"
        }
    ],
    "description": [
        {
            "languageCode": "nb",
            "languageText": "UttrekkSkattemelding v0_18 datasett skattepliktig kundeutbytte utenfor virksomhet per utbetaler"
        }
    ],
    "administrativeStatus": "DRAFT",
    "versionValidFrom": "2019-07-01T13:48:44.000Z",
    "validFrom": "2019-07-01T13:48:44.000Z",
    "createdDate": "2019-07-01T13:48:44.000Z",
    "createdBy": "BNJ",
    "unitDataStructure": "/UnitDataStructure/e322f937-3089-4de4-a5c7-7b7f4e826a27",
    "dataSetState": "INPUT_DATA",
    "temporalityType": "EVENT"
}